kbbridge/__init__.py
kbbridge/logger.py
kbbridge/server.py
kbbridge/config/__init__.py
kbbridge/config/config.py
kbbridge/config/constants.py
kbbridge/config/env_loader.py
kbbridge/core/__init__.py
kbbridge/core/discovery/__init__.py
kbbridge/core/discovery/file_discover.py
kbbridge/core/discovery/file_reranker.py
kbbridge/core/extraction/__init__.py
kbbridge/core/extraction/content_cluster.py
kbbridge/core/extraction/paragraph_locator.py
kbbridge/core/orchestration/__init__.py
kbbridge/core/orchestration/models.py
kbbridge/core/orchestration/pipeline.py
kbbridge/core/orchestration/services.py
kbbridge/core/orchestration/utils.py
kbbridge/core/query/__init__.py
kbbridge/core/query/constants.py
kbbridge/core/query/intention_extractor.py
kbbridge/core/query/keyword_generator.py
kbbridge/core/query/models.py
kbbridge/core/query/rewriter.py
kbbridge/core/reflection/__init__.py
kbbridge/core/reflection/config.py
kbbridge/core/reflection/constants.py
kbbridge/core/reflection/evaluator.py
kbbridge/core/reflection/feedback.py
kbbridge/core/reflection/integration.py
kbbridge/core/reflection/models.py
kbbridge/core/reflection/reflector.py
kbbridge/core/synthesis/__init__.py
kbbridge/core/synthesis/answer_extractor.py
kbbridge/core/synthesis/answer_formatter.py
kbbridge/core/synthesis/answer_reranker.py
kbbridge/core/synthesis/constants.py
kbbridge/core/utils/__init__.py
kbbridge/core/utils/json_utils.py
kbbridge/core/utils/profiling_utils.py
kbbridge/core/utils/text_processing_utils.py
kbbridge/integrations/__init__.py
kbbridge/integrations/backend_adapter.py
kbbridge/integrations/credentials.py
kbbridge/integrations/retriever_base.py
kbbridge/integrations/retriever_router.py
kbbridge/integrations/dify/__init__.py
kbbridge/integrations/dify/constants.py
kbbridge/integrations/dify/dify_backend_adapter.py
kbbridge/integrations/dify/dify_credentials.py
kbbridge/integrations/dify/dify_retriever.py
kbbridge/middleware/__init__.py
kbbridge/middleware/_auth_core.py
kbbridge-0.3.0.dist-info/METADATA
kbbridge-0.3.0.dist-info/WHEEL
kbbridge-0.3.0.dist-info/top_level.txt
kbbridge-0.3.0.dist-info/RECORD
