Metadata-Version: 2.4
Name: kbbridge
Version: 0.3.0
Summary: MCP server for intelligent knowledge base search and retrieval with Dify integration
Author-email: Wen-Ting Wang <egpivo@gmail.com>
License: Apache-2.0
Project-URL: Homepage, https://github.com/egpivo/kb-bridge
Project-URL: Documentation, https://github.com/egpivo/kb-bridge/blob/main/README.md
Project-URL: Source, https://github.com/egpivo/kb-bridge.git
Project-URL: Bug Tracker, https://github.com/egpivo/kb-bridge/issues
Requires-Python: >=3.12
Requires-Dist: aiohttp>=3.11.18
Requires-Dist: fastmcp>=2.11.0
Requires-Dist: mcp>=1.15.0
Requires-Dist: pydantic>=2.11.3
Requires-Dist: python-dotenv>=1.0.0
Requires-Dist: dspy>=2.4.0
Requires-Dist: uvicorn>=0.31.0
Requires-Dist: fastapi>=0.116.1
Requires-Dist: starlette>=0.27.0
Provides-Extra: dev
Requires-Dist: pytest>=8.3.5; extra == "dev"
Requires-Dist: pytest-asyncio>=0.26.0; extra == "dev"
Requires-Dist: pytest-cov>=6.2.1; extra == "dev"
Requires-Dist: pytest-mock>=3.10.0; extra == "dev"
Requires-Dist: pytest-xdist>=3.5.0; extra == "dev"
Requires-Dist: coverage>=7.0.0; extra == "dev"
Requires-Dist: ruff>=0.9.7; extra == "dev"
Requires-Dist: bump2version>=1.0.1; extra == "dev"
